backplate/__init__.py
backplate/api.py
backplate/errors.py
backplate/mediatypes.py
backplate/routing.py
backplate/throttling.py
backplate-0.4.0.dist-info/DESCRIPTION.rst
backplate-0.4.0.dist-info/METADATA
backplate-0.4.0.dist-info/RECORD
backplate-0.4.0.dist-info/WHEEL
backplate-0.4.0.dist-info/metadata.json
backplate-0.4.0.dist-info/top_level.txt
